pytilpack/__init__.py
pytilpack/anthropic.py
pytilpack/base64.py
pytilpack/cache.py
pytilpack/csv.py
pytilpack/data_url.py
pytilpack/dataclasses.py
pytilpack/datetime.py
pytilpack/flask_login.py
pytilpack/fnctl.py
pytilpack/functools.py
pytilpack/healthcheck.py
pytilpack/htmlrag.py
pytilpack/http.py
pytilpack/httpx.py
pytilpack/importlib.py
pytilpack/json.py
pytilpack/logging.py
pytilpack/markdown.py
pytilpack/msal.py
pytilpack/openai.py
pytilpack/paginator.py
pytilpack/pathlib.py
pytilpack/py.typed
pytilpack/pycrypto.py
pytilpack/pydantic.py
pytilpack/pytest.py
pytilpack/python.py
pytilpack/quart_auth.py
pytilpack/random.py
pytilpack/secrets.py
pytilpack/sse.py
pytilpack/threading.py
pytilpack/threadinga.py
pytilpack/tiktoken.py
pytilpack/tqdm.py
pytilpack/typing.py
pytilpack/web.py
pytilpack/yaml.py
pytilpack/asyncio/__init__.py
pytilpack/asyncio/functools_.py
pytilpack/asyncio/io_.py
pytilpack/asyncio/jobrunner.py
pytilpack/asyncio/misc.py
pytilpack/asyncio/threadpool.py
pytilpack/cli/__init__.py
pytilpack/cli/delete_empty_dirs.py
pytilpack/cli/delete_old_files.py
pytilpack/cli/fetch.py
pytilpack/cli/main.py
pytilpack/cli/mcp.py
pytilpack/cli/sync.py
pytilpack/cli/wait_for_db_connection.py
pytilpack/fastapi/__init__.py
pytilpack/fastapi/asserts.py
pytilpack/flask/__init__.py
pytilpack/flask/asserts.py
pytilpack/flask/misc.py
pytilpack/flask/proxy_fix.py
pytilpack/quart/__init__.py
pytilpack/quart/asserts.py
pytilpack/quart/misc.py
pytilpack/quart/proxy_fix.py
pytilpack/sqlalchemy/__init__.py
pytilpack/sqlalchemy/async_.py
pytilpack/sqlalchemy/describe.py
pytilpack/sqlalchemy/flask.py
pytilpack/sqlalchemy/sync.py
pytilpack-1.39.2.dist-info/METADATA
pytilpack-1.39.2.dist-info/WHEEL
pytilpack-1.39.2.dist-info/entry_points.txt
pytilpack-1.39.2.dist-info/licenses/LICENSE
pytilpack-1.39.2.dist-info/RECORD
