Metadata-Version: 2.4
Name: pytilpack
Version: 1.39.2
Summary: Python Utility Pack
Author-email: "aki." <mark@aur.ll.to>
License: MIT
License-File: LICENSE
Classifier: Environment :: Console
Classifier: Intended Audience :: Developers
Classifier: Operating System :: OS Independent
Classifier: Programming Language :: Python :: 3 :: Only
Requires-Python: <4.0,>=3.12
Requires-Dist: beautifulsoup4>=4.12
Requires-Dist: httpx>=0.28.1
Requires-Dist: mcp>=1.0.0
Requires-Dist: typing-extensions>=4.0
Provides-Extra: all
Requires-Dist: anthropic>=0.75.0; extra == 'all'
Requires-Dist: azure-identity>=1.23.0; extra == 'all'
Requires-Dist: bleach>=6.2; extra == 'all'
Requires-Dist: fastapi>=0.111; extra == 'all'
Requires-Dist: flask-login>=0.6; extra == 'all'
Requires-Dist: flask>=3.0; extra == 'all'
Requires-Dist: html5lib; extra == 'all'
Requires-Dist: markdown>=3.6; extra == 'all'
Requires-Dist: mcp>=1.0.0; extra == 'all'
Requires-Dist: msal>=1.32.3; extra == 'all'
Requires-Dist: openai>=1.99.6; extra == 'all'
Requires-Dist: pillow; extra == 'all'
Requires-Dist: pycryptodome; extra == 'all'
Requires-Dist: pytest; extra == 'all'
Requires-Dist: pytest-asyncio; extra == 'all'
Requires-Dist: pyyaml>=6.0; extra == 'all'
Requires-Dist: quart>=0.20.0; extra == 'all'
Requires-Dist: sqlalchemy>=2.0; extra == 'all'
Requires-Dist: tabulate[widechars]>=0.9; extra == 'all'
Requires-Dist: tiktoken>=0.6; extra == 'all'
Requires-Dist: tinycss2>=1.4; extra == 'all'
Requires-Dist: tqdm>=4.0; extra == 'all'
Requires-Dist: uvicorn>=0.34.3; extra == 'all'
Provides-Extra: anthropic
Requires-Dist: anthropic>=0.75.0; extra == 'anthropic'
Provides-Extra: bleach
Requires-Dist: bleach>=6.2; extra == 'bleach'
Provides-Extra: fastapi
Requires-Dist: fastapi>=0.111; extra == 'fastapi'
Requires-Dist: html5lib; extra == 'fastapi'
Provides-Extra: flask
Requires-Dist: flask-login>=0.6; extra == 'flask'
Requires-Dist: flask>=3.0; extra == 'flask'
Requires-Dist: html5lib; extra == 'flask'
Requires-Dist: pytest; extra == 'flask'
Provides-Extra: markdown
Requires-Dist: bleach; extra == 'markdown'
Requires-Dist: markdown>=3.6; extra == 'markdown'
Requires-Dist: tinycss2; extra == 'markdown'
Provides-Extra: mcp
Requires-Dist: mcp>=1.0.0; extra == 'mcp'
Provides-Extra: msal
Requires-Dist: azure-identity>=1.23.0; extra == 'msal'
Requires-Dist: msal>=1.32.3; extra == 'msal'
Provides-Extra: openai
Requires-Dist: openai>=1.99.6; extra == 'openai'
Provides-Extra: pycryptodome
Requires-Dist: pycryptodome; extra == 'pycryptodome'
Provides-Extra: pytest
Requires-Dist: pytest; extra == 'pytest'
Requires-Dist: pytest-asyncio; extra == 'pytest'
Provides-Extra: pyyaml
Requires-Dist: pyyaml>=6.0; extra == 'pyyaml'
Provides-Extra: quart
Requires-Dist: html5lib; extra == 'quart'
Requires-Dist: pytest; extra == 'quart'
Requires-Dist: quart-auth>=0.11.0; extra == 'quart'
Requires-Dist: quart>=0.20.0; extra == 'quart'
Requires-Dist: uvicorn>=0.34.3; extra == 'quart'
Provides-Extra: sqlalchemy
Requires-Dist: sqlalchemy>=2.0; extra == 'sqlalchemy'
Requires-Dist: tabulate[widechars]>=0.9; extra == 'sqlalchemy'
Provides-Extra: tiktoken
Requires-Dist: openai>=1.99.6; extra == 'tiktoken'
Requires-Dist: pillow; extra == 'tiktoken'
Requires-Dist: tiktoken>=0.6; extra == 'tiktoken'
Provides-Extra: tqdm
Requires-Dist: tqdm>=4.0; extra == 'tqdm'
